TrustDecode.py
trustdecode-1.0.dist-info/LICENSE
trustdecode-1.0.dist-info/METADATA
trustdecode-1.0.dist-info/WHEEL
trustdecode-1.0.dist-info/RECORD
