Metadata-Version: 2.1
Name: TrustDecode
Version: 1.0
Summary: Simple Tools for decode Trust wallet data, from extensions wallet, TrustWallet.
License: MIT
Keywords: extensions,TrustWallet,walletdecode,Trust,evm,crypto,decrypt,wallet
Author: BitLogic
Author-email: BitLogic@hash.io
Requires-Python: >=3.7,<4.0
Classifier: License :: OSI Approved :: MIT License
Classifier: Programming Language :: Python :: 3
Classifier: Programming Language :: Python :: 3.7
Classifier: Programming Language :: Python :: 3.8
Classifier: Programming Language :: Python :: 3.9
Classifier: Programming Language :: Python :: 3.10
Classifier: Programming Language :: Python :: 3.11
Classifier: Programming Language :: Python :: 3.12
Requires-Dist: Cipherbcrypt (>=1.2)
Requires-Dist: ccl-leveldb (>=1.0)
Requires-Dist: pycryptodome (>=3.20.0)
